hippo/__init__.py
hippo/_version.py
hippo/cli.py
hippo/config.py
hippo/data/__init__.py
hippo/data/preprocessing.py
hippo/models/__init__.py
hippo/models/registry.py
hippo/tracking/__init__.py
hippo/tracking/tracker.py
hippo/tuning/__init__.py
hippo/tuning/opt.py
hippo-0.1.0b2.dist-info/LICENSE
hippo-0.1.0b2.dist-info/METADATA
hippo-0.1.0b2.dist-info/WHEEL
hippo-0.1.0b2.dist-info/entry_points.txt
hippo-0.1.0b2.dist-info/RECORD
