Metadata-Version: 2.3
Name: hippo
Version: 0.1.0b2
Summary: Hippo is a lightweight machine-learning framework that unifies declarative preprocessing pipelines, automatic hyperparameter optimisation, and local experiment tracking behind a single, friendly CLI.
License: MIT
Author: Alexey
Author-email: axbelenkov@gmail.com
Requires-Python: >=3.10
Classifier: License :: OSI Approved :: MIT License
Classifier: Programming Language :: Python :: 3
Classifier: Programming Language :: Python :: 3.10
Classifier: Programming Language :: Python :: 3.11
Classifier: Programming Language :: Python :: 3.12
Classifier: Programming Language :: Python :: 3.13
Requires-Dist: PyYAML (>=6.0)
Requires-Dist: joblib (>=1.4)
Requires-Dist: optuna (>=3.6)
Requires-Dist: scikit-learn (>=1.5)
Requires-Dist: xgboost (>=2.0)
